LICENSE
MANIFEST.in
README.md
requirements.txt
setup.py
datrool_exchanges.egg-info/PKG-INFO
datrool_exchanges.egg-info/SOURCES.txt
datrool_exchanges.egg-info/dependency_links.txt
datrool_exchanges.egg-info/requires.txt
datrool_exchanges.egg-info/top_level.txt
src/__init__.py
src/binance.py
src/lib/__init__.py
src/lib/exchange.py
src/lib/helpers.py
src/lib/position_exchange.py
src/lib/spot_exchange.py
src/lib/test_wrapper.py
tests/test_binance.py
tests/test_exchange.py
tests/test_position.py
tests/test_symbol.py