Metadata-Version: 2.1
Name: datrool-exchanges
Version: 1.0.3
Summary: Exchange wrappers for the datrool project
Home-page: https://gitlab.com/datrool/core/exchanges
Author: Patrik Katrenak
Author-email: patrik@katryapps.com
Platform: any
Classifier: Programming Language :: Python :: 3
Classifier: Operating System :: OS Independent
Classifier: Natural Language :: English
Requires-Python: >=3.10
License-File: LICENSE
Requires-Dist: orjson==3.9.15
Requires-Dist: websockets==12.0
